[{"name":"Aster.Aries","y":0.5714285714,"drilldown":"Aster.Aries Win Rate"},{"name":"CDEC ","y":0.3333333333,"drilldown":"CDEC  Win Rate"},{"name":"EHOME","y":1.0,"drilldown":"EHOME Win Rate"},{"name":"Elephant","y":0.8,"drilldown":"Elephant Win Rate"},{"name":"LBZS","y":0.0,"drilldown":"LBZS Win Rate"},{"name":"Royal Never Give Up","y":0.6,"drilldown":"Royal Never Give Up Win Rate"},{"name":"Sparking Arrow Gaming","y":0.4,"drilldown":"Sparking Arrow Gaming Win Rate"},{"name":"Team Magma","y":0.5714285714,"drilldown":"Team Magma Win Rate"},{"name":"Xtreme\u00a0 Gaming","y":0.0,"drilldown":"Xtreme\u00a0 Gaming Win Rate"},{"name":"phoenix gaming","y":0.3333333333,"drilldown":"phoenix gaming Win Rate"}]