[{"name":"Templar Assassin","y":35,"drilldown":"Templar Assassin Picks"},{"name":"Broodmother","y":14,"drilldown":"Broodmother Picks"},{"name":"Ancient Apparition","y":44,"drilldown":"Ancient Apparition Picks"},{"name":"Mars","y":57,"drilldown":"Mars Picks"},{"name":"Puck","y":37,"drilldown":"Puck Picks"},{"name":"Viper","y":18,"drilldown":"Viper Picks"},{"name":"Timbersaw","y":26,"drilldown":"Timbersaw Picks"},{"name":"Nyx Assassin","y":24,"drilldown":"Nyx Assassin Picks"},{"name":"Ursa","y":21,"drilldown":"Ursa Picks"},{"name":"Faceless Void","y":22,"drilldown":"Faceless Void Picks"},{"name":"Terrorblade","y":28,"drilldown":"Terrorblade Picks"},{"name":"Lion","y":61,"drilldown":"Lion Picks"},{"name":"Enchantress","y":35,"drilldown":"Enchantress Picks"},{"name":"Dragon Knight","y":43,"drilldown":"Dragon Knight Picks"},{"name":"Spectre","y":24,"drilldown":"Spectre Picks"},{"name":"Phantom Lancer","y":11,"drilldown":"Phantom Lancer Picks"},{"name":"Morphling","y":22,"drilldown":"Morphling Picks"},{"name":"Leshrac","y":24,"drilldown":"Leshrac Picks"},{"name":"Phoenix","y":35,"drilldown":"Phoenix Picks"},{"name":"Wraith King","y":20,"drilldown":"Wraith King Picks"},{"name":"Batrider","y":11,"drilldown":"Batrider Picks"},{"name":"Snapfire","y":38,"drilldown":"Snapfire Picks"},{"name":"Lina","y":22,"drilldown":"Lina Picks"},{"name":"Tiny","y":27,"drilldown":"Tiny Picks"},{"name":"Invoker","y":19,"drilldown":"Invoker Picks"},{"name":"Winter Wyvern","y":33,"drilldown":"Winter Wyvern Picks"},{"name":"Ember Spirit","y":16,"drilldown":"Ember Spirit Picks"},{"name":"Doom","y":19,"drilldown":"Doom Picks"},{"name":"Magnus","y":25,"drilldown":"Magnus Picks"},{"name":"Dark Seer","y":15,"drilldown":"Dark Seer Picks"},{"name":"Razor","y":11,"drilldown":"Razor Picks"},{"name":"Tidehunter","y":11,"drilldown":"Tidehunter Picks"},{"name":"Storm Spirit","y":15,"drilldown":"Storm Spirit Picks"},{"name":"Death Prophet","y":14,"drilldown":"Death Prophet Picks"},{"name":"Dark Willow","y":23,"drilldown":"Dark Willow Picks"},{"name":"Grimstroke","y":24,"drilldown":"Grimstroke Picks"},{"name":"Luna","y":13,"drilldown":"Luna Picks"},{"name":"Lifestealer","y":8,"drilldown":"Lifestealer Picks"},{"name":"Axe","y":20,"drilldown":"Axe Picks"},{"name":"Medusa","y":12,"drilldown":"Medusa Picks"},{"name":"Clockwerk","y":19,"drilldown":"Clockwerk Picks"},{"name":"Abaddon","y":14,"drilldown":"Abaddon Picks"},{"name":"Juggernaut","y":8,"drilldown":"Juggernaut Picks"},{"name":"Void Spirit","y":11,"drilldown":"Void Spirit Picks"},{"name":"Io","y":4,"drilldown":"Io Picks"},{"name":"Monkey King","y":9,"drilldown":"Monkey King Picks"},{"name":"Centaur Warrunner","y":12,"drilldown":"Centaur Warrunner Picks"},{"name":"Legion Commander","y":4,"drilldown":"Legion Commander Picks"},{"name":"Elder Titan","y":18,"drilldown":"Elder Titan Picks"},{"name":"Oracle","y":11,"drilldown":"Oracle Picks"},{"name":"Treant Protector","y":15,"drilldown":"Treant Protector Picks"},{"name":"Hoodwink","y":14,"drilldown":"Hoodwink Picks"},{"name":"Bristleback","y":9,"drilldown":"Bristleback Picks"},{"name":"Venomancer","y":6,"drilldown":"Venomancer Picks"},{"name":"Kunkka","y":9,"drilldown":"Kunkka Picks"},{"name":"Drow Ranger","y":6,"drilldown":"Drow Ranger Picks"},{"name":"Earth Spirit","y":16,"drilldown":"Earth Spirit Picks"},{"name":"Troll Warlord","y":6,"drilldown":"Troll Warlord Picks"},{"name":"Warlock","y":14,"drilldown":"Warlock Picks"},{"name":"Gyrocopter","y":7,"drilldown":"Gyrocopter Picks"},{"name":"Naga Siren","y":5,"drilldown":"Naga Siren Picks"},{"name":"Shadow Demon","y":9,"drilldown":"Shadow Demon Picks"},{"name":"Slardar","y":5,"drilldown":"Slardar Picks"},{"name":"Anti-Mage","y":3,"drilldown":"Anti-Mage Picks"},{"name":"Nature's Prophet","y":8,"drilldown":"Nature's Prophet Picks"},{"name":"Bloodseeker","y":6,"drilldown":"Bloodseeker Picks"},{"name":"Sand King","y":8,"drilldown":"Sand King Picks"},{"name":"Phantom Assassin","y":6,"drilldown":"Phantom Assassin Picks"},{"name":"Mirana","y":11,"drilldown":"Mirana Picks"},{"name":"Rubick","y":10,"drilldown":"Rubick Picks"},{"name":"Underlord","y":4,"drilldown":"Underlord Picks"},{"name":"Windranger","y":9,"drilldown":"Windranger Picks"},{"name":"Shadow Shaman","y":9,"drilldown":"Shadow Shaman Picks"},{"name":"Beastmaster","y":6,"drilldown":"Beastmaster Picks"},{"name":"Lycan","y":2,"drilldown":"Lycan Picks"},{"name":"Sven","y":5,"drilldown":"Sven Picks"},{"name":"Pangolier","y":5,"drilldown":"Pangolier Picks"},{"name":"Disruptor","y":7,"drilldown":"Disruptor Picks"},{"name":"Tusk","y":7,"drilldown":"Tusk Picks"},{"name":"Skywrath Mage","y":6,"drilldown":"Skywrath Mage Picks"},{"name":"Witch Doctor","y":5,"drilldown":"Witch Doctor Picks"},{"name":"Shadow Fiend","y":4,"drilldown":"Shadow Fiend Picks"},{"name":"Slark","y":3,"drilldown":"Slark Picks"},{"name":"Chaos Knight","y":2,"drilldown":"Chaos Knight Picks"},{"name":"Undying","y":3,"drilldown":"Undying Picks"},{"name":"Night Stalker","y":2,"drilldown":"Night Stalker Picks"},{"name":"Pugna","y":1,"drilldown":"Pugna Picks"},{"name":"Omniknight","y":2,"drilldown":"Omniknight Picks"},{"name":"Arc Warden","y":1,"drilldown":"Arc Warden Picks"},{"name":"Lone Druid","y":3,"drilldown":"Lone Druid Picks"},{"name":"Queen of Pain","y":1,"drilldown":"Queen of Pain Picks"},{"name":"Bane","y":2,"drilldown":"Bane Picks"},{"name":"Crystal Maiden","y":2,"drilldown":"Crystal Maiden Picks"},{"name":"Dazzle","y":2,"drilldown":"Dazzle Picks"},{"name":"Brewmaster","y":2,"drilldown":"Brewmaster Picks"},{"name":"Chen","y":1,"drilldown":"Chen Picks"},{"name":"Enigma","y":0,"drilldown":"Enigma Picks"},{"name":"Necrophos","y":0,"drilldown":"Necrophos Picks"},{"name":"Huskar","y":1,"drilldown":"Huskar Picks"},{"name":"Weaver","y":1,"drilldown":"Weaver Picks"},{"name":"Jakiro","y":1,"drilldown":"Jakiro Picks"},{"name":"Outworld Devourer","y":1,"drilldown":"Outworld Devourer Picks"},{"name":"Riki","y":0,"drilldown":"Riki Picks"},{"name":"Earthshaker","y":0,"drilldown":"Earthshaker Picks"},{"name":"Pudge","y":0,"drilldown":"Pudge Picks"},{"name":"Vengeful Spirit","y":0,"drilldown":"Vengeful Spirit Picks"},{"name":"Zeus","y":0,"drilldown":"Zeus Picks"},{"name":"Lich","y":0,"drilldown":"Lich Picks"},{"name":"Tinker","y":0,"drilldown":"Tinker Picks"},{"name":"Sniper","y":0,"drilldown":"Sniper Picks"},{"name":"Clinkz","y":0,"drilldown":"Clinkz Picks"},{"name":"Bounty Hunter","y":0,"drilldown":"Bounty Hunter Picks"},{"name":"Spirit Breaker","y":0,"drilldown":"Spirit Breaker Picks"},{"name":"Alchemist","y":0,"drilldown":"Alchemist Picks"},{"name":"Silencer","y":0,"drilldown":"Silencer Picks"},{"name":"Meepo","y":0,"drilldown":"Meepo Picks"},{"name":"Ogre Magi","y":0,"drilldown":"Ogre Magi Picks"},{"name":"Keeper of the Light","y":0,"drilldown":"Keeper of the Light Picks"},{"name":"Visage","y":0,"drilldown":"Visage Picks"},{"name":"Techies","y":0,"drilldown":"Techies Picks"},{"name":"Dawnbreaker","y":0,"drilldown":"Dawnbreaker Picks"}]